seatconnect/__init__.py
seatconnect/__version__.py
seatconnect/connection.py
seatconnect/const.py
seatconnect/dashboard.py
seatconnect/exceptions.py
seatconnect/utilities.py
seatconnect/vehicle.py
seatconnect-1.1.9.dist-info/LICENSE
seatconnect-1.1.9.dist-info/METADATA
seatconnect-1.1.9.dist-info/WHEEL
seatconnect-1.1.9.dist-info/top_level.txt
seatconnect-1.1.9.dist-info/RECORD
