Metadata-Version: 2.1
Name: seatconnect
Version: 1.1.9
Summary: Communicate with Seat Connect
Home-page: https://github.com/farfar/seatconnect
Author: Farfar
Author-email: faekie@hotmail.com
Provides: seatconnect
License-File: LICENSE
Requires-Dist: aiohttp
Requires-Dist: beautifulsoup4
Requires-Dist: cryptography
Requires-Dist: lxml
Requires-Dist: pyjwt
Requires-Dist: xmltodict
